{
    "botId": 1000000497,
    "key": "key",
    "value": "{\"menu\":{\"additionalDisplay\":null,\"status\":null,\"name\":\"Menu\",\"answers\":[{\"payload\":{\"text\":\"The menu contains a lot of items\\n\",\"media\":null,\"elements\":null,\"buttons\":null},\"response_type\":\"TEXT\"}],\"questions\":[\"What is in the menu\",\"Where can i find the menu \",\"How is the menu\"],\"sample_request\":\"What is in the menu|Where can i find the menu |How is the menu|What constitute in the menu|What is in the fare|Where can i recover the menu |Where can i find the carte du jour |How exist the menu|What is in the carte|What comprise in the menu|How equal the menu|What is in the computer menu|How be the menu|How make up the menu|What be in the menu|What is in the bill of fare|Where can i retrieve the menu |Where can i regain the menu |Where can i feel the menu |How is the card|What represent in the menu|Where can i find the bill of fare |What cost in the menu|What is in the card|What embody in the menu|What follow in the menu|Where can i come up the menu |How follow the menu|Where can i determine the menu |What make up in the menu|Where can i receive the menu |How is the carte|Where can i encounter the menu |Where can i find out the menu |How constitute the menu|Where can i discover the menu |Where can i find the computer menu |Where can i find the fare |How is the carte du jour|Where can i find the carte |How live the menu|How is the menu|What live in the menu|Where can i ascertain the menu |Where can i find oneself the menu |Where can i line up the menu |Where can i bump the menu |What is in the menu|Where can i incur the menu |Where can i chance the menu |How cost the menu|Where can i rule the menu |How embody the menu|Where can i see the menu |What is in the carte du jour|Where can i happen the menu |How comprise the menu|Where can i find the menu |Where can i get the menu |What exist in the menu|Where can i observe the menu |Where can i get hold the menu |Where can i witness the menu |Where can i notice the menu |Where can i detect the menu |How is the fare|How represent the menu|How is the computer menu|What equal in the menu|What personify in the menu|Where can i find the card |How is the bill of fare|Where can i obtain the menu |How personify the menu\",\"slotted\":false,\"follow\":\"appreciate\",\"fulfill\":\"internal\",\"response\":[{\"text\":\"The menu contains a lot of items\\n\",\"attachment\":{}}],\"fulfill_status\":true,\"follow_message\":[{\"text\":\"follow message\"}]},\"support\":{\"additionalDisplay\":null,\"status\":null,\"name\":\"Support\",\"answers\":[{\"payload\":{\"text\":\"THis is wonderful\",\"media\":null,\"elements\":null,\"buttons\":null},\"response_type\":\"TEXT\"}],\"questions\":[],\"sample_request\":\"\",\"slotted\":false,\"follow\":\"appreciate\",\"fulfill\":\"internal\",\"response\":[{\"text\":\"THis is wonderful\",\"attachment\":{}}],\"fulfill_status\":true,\"follow_message\":[{\"text\":\"follow message\"}]},\"contact\":{\"additionalDisplay\":null,\"status\":null,\"name\":\"contact\",\"answers\":[{\"payload\":{\"text\":\"THis is the website . You have to go through all these things to contact me\",\"media\":null,\"elements\":null,\"buttons\":null},\"response_type\":\"TEXT\"}],\"questions\":[\"how to contact you\",\"why to contact you\",\"where to contact you\"],\"sample_request\":\"how to contact you|why to contact you|where to contact you|how to get hold of you|how to touch you|why to touch you|why to get hold of you|how to reach you|why to reach you|why to get through you|how to contact you|how to meet you|where to contact you|where to meet you|why to meet you|where to touch you|where to get hold of you|why to adjoin you|where to reach you|where to adjoin you|where to get through you|how to get through you|how to adjoin you|why to contact you\",\"slotted\":false,\"follow\":\"appreciate\",\"fulfill\":\"internal\",\"response\":[{\"text\":\"THis is the website . You have to go through all these things to contact me\",\"attachment\":{}}],\"fulfill_status\":true,\"follow_message\":[{\"text\":\"follow message\"}]}}"
}
